[
    {
        "id": 1,
        "name": "Мега пачка чипсонов",
        "img": "1.jpg",
        "price": 12.50,
        "fullDesc": "Чипсы краб стоявшие на полке 10 дней",
        "desc": "Супер крутая пачка чипсов, для тех кто не любит детей"
    },
    {
        "id": 2,
        "name": "10 Детей",
        "img": "2.jpg",
        "price": 20.50,
        "fullDesc": "10 детей от 2 до 15 лет",
        "desc": "Не обязательно чёрных"
    },
    {
        "id": 3,
        "name": "Стать годжо сатору",
        "img": "3.jpg",
        "price": 200,
        "fullDesc": "Сильнейший маг",
        "desc": "Ты сатору гождо потому что ты сатору годжо"
    },
    {
        "id": 4,
        "name": "Закончить все войны",
        "img": "4.png",
        "price": 2,
        "fullDesc": "Самый мировой мир",
        "desc": "Мировой мир"
    }
]